evoflow/__init__.py
evoflow/config.py
evoflow/io.py
evoflow/population.py
evoflow/utils.py
evoflow/backend/__init__.py
evoflow/backend/common.py
evoflow/backend/cupy.py
evoflow/backend/load_backend.py
evoflow/backend/numpy.py
evoflow/backend/tensorflow.py
evoflow/backend/tf_ops/__init__.py
evoflow/backend/tf_ops/assign.py
evoflow/backend/tf_ops/randint.py
evoflow/callbacks/__init__.py
evoflow/callbacks/callback.py
evoflow/callbacks/dummy.py
evoflow/engine/__init__.py
evoflow/engine/callback_collection.py
evoflow/engine/evoflow.py
evoflow/engine/fitness_function.py
evoflow/engine/input.py
evoflow/engine/op.py
evoflow/engine/results.py
evoflow/engine/selection_strategy.py
evoflow/fitness/__init__.py
evoflow/fitness/cosine_similarity.py
evoflow/fitness/sum.py
evoflow/ops/__init__.py
evoflow/ops/core.py
evoflow/ops/dual_crossover.py
evoflow/ops/random_mutation.py
evoflow/ops/reverse.py
evoflow/ops/shuffle.py
evoflow/ops/single_crossover.py
evoflow/ops/uniform_crossover.py
evoflow/selection/__init__.py
evoflow/selection/select_fittest.py
tests/__init__.py
tests/conftest.py
tests/test_config.py
tests/test_io.py
tests/test_population.py
tests/test_utils.py
tests/backend/__init__.py
tests/backend/test_common.py
tests/backend/test_indexing.py
tests/backend/test_initialization.py
tests/backend/test_manipulation.py
tests/backend/test_math.py
tests/backend/test_random.py
tests/backend/test_reduce.py
tests/backend/test_statistical.py
tests/backend/test_utils.py
tests/engine/__init__.py
tests/engine/test_inputs.py
tests/engine/test_op.py
tests/fitness/__init__.py
tests/fitness/test_cosine_similarity.py
tests/fitness/test_sum.py
tests/ops/__init__.py
tests/ops/test_dual_crossover.py
tests/ops/test_random_mutation.py
tests/ops/test_reverse.py
tests/ops/test_shuffle.py
tests/ops/test_single_crossover.py
tests/ops/test_uniform_crossover.py
tests/tensorflow_compile/__init__.py
tests/tensorflow_compile/test_assign.py
tests/tensorflow_compile/test_randint.py
evoflow-0.5.2.post1592070199.dist-info/LICENSE
evoflow-0.5.2.post1592070199.dist-info/METADATA
evoflow-0.5.2.post1592070199.dist-info/WHEEL
evoflow-0.5.2.post1592070199.dist-info/top_level.txt
evoflow-0.5.2.post1592070199.dist-info/RECORD
