Metadata-Version: 2.1
Name: evoflow
Version: 0.5.2-1592070199
Summary: Genetic algorithms for humans
Home-page: https://github.com/google/evoflow
Author: Elie Bursztein
Author-email: evoflow@google.com
License: Apache 2
Platform: UNKNOWN
Classifier: Development Status :: 5 - Production/Stable
Classifier: Intended Audience :: Developers
Classifier: Intended Audience :: Education
Classifier: Intended Audience :: Science/Research
Classifier: License :: OSI Approved :: MIT License
Classifier: Programming Language :: Python :: 3
Classifier: Programming Language :: Python :: 3.6
Classifier: Topic :: Software Development :: Libraries
Classifier: Topic :: Software Development :: Libraries :: Python Modules
Requires-Python: >=3
Requires-Dist: networkx
Requires-Dist: numpy
Requires-Dist: tqdm
Requires-Dist: tabulate
Requires-Dist: termcolor
Requires-Dist: matplotlib
Requires-Dist: altair
Requires-Dist: tensorflow (>=2.2.0)
Requires-Dist: pandas
Requires-Dist: perfcounters
